acon/AutoML.py
acon/__init__.py
acon/adaptation.py
acon/adaptive_hyperparameter_tuner.py
acon/adaptive_neural_architecture_search.py
acon/correlation_modules.py
acon/data_mapping.py
acon/gradient_slice_sorting.py
acon/hyperparameter_tuner.py
acon/loss_function.py
acon/meta_learning.py
acon/optimization.py
acon/real_time_integration.py
acon-0.1.1.dist-info/LICENSE
acon-0.1.1.dist-info/METADATA
acon-0.1.1.dist-info/WHEEL
acon-0.1.1.dist-info/top_level.txt
acon-0.1.1.dist-info/RECORD
